quorum/__init__.py
quorum/acl.py
quorum/amazon.py
quorum/amqp.py
quorum/base.py
quorum/common.py
quorum/config.py
quorum/crypt.py
quorum/daemon.py
quorum/data.py
quorum/date.py
quorum/defines.py
quorum/errors.py
quorum/exceptions.py
quorum/execution.py
quorum/export.py
quorum/extras.py
quorum/formats.py
quorum/httpc.py
quorum/info.py
quorum/jsonf.py
quorum/legacy.py
quorum/log.py
quorum/mail.py
quorum/meta.py
quorum/model.py
quorum/mongodb.py
quorum/observer.py
quorum/pusherc.py
quorum/redisdb.py
quorum/request.py
quorum/route.py
quorum/session.py
quorum/storage.py
quorum/structures.py
quorum/template.py
quorum/typesf.py
quorum/unit_test.py
quorum/util.py
quorum/validation.py
quorum/test/__init__.py
quorum/test/acl.py
quorum/test/amazon.py
quorum/test/base.py
quorum/test/config.py
quorum/test/crypt.py
quorum/test/data.py
quorum/test/execution.py
quorum/test/export.py
quorum/test/httpc.py
quorum/test/log.py
quorum/test/mail.py
quorum/test/mock.py
quorum/test/model.py
quorum/test/mongodb.py
quorum/test/structures.py
quorum/test/typesf.py
quorum/test/util.py
quorum/test/validation.py
quorum-0.8.7.dist-info/METADATA
quorum-0.8.7.dist-info/WHEEL
quorum-0.8.7.dist-info/top_level.txt
quorum-0.8.7.dist-info/zip-safe
quorum-0.8.7.dist-info/RECORD
